{"id":"3Bt4","dependencies":[{"name":"c:\\Users\\kotka\\Dev\\hrafnkellbaldurs.github.io\\hrafnkellbaldurs.github.io\\package.json","includedInParent":true,"mtime":1532872086649},{"name":"./favicon.png","dynamic":true,"parent":"c:\\Users\\kotka\\Dev\\hrafnkellbaldurs.github.io\\hrafnkellbaldurs.github.io\\index2.html","resolved":"c:\\Users\\kotka\\Dev\\hrafnkellbaldurs.github.io\\hrafnkellbaldurs.github.io\\favicon.png"},{"name":"./src\\index.js","dynamic":true,"parent":"c:\\Users\\kotka\\Dev\\hrafnkellbaldurs.github.io\\hrafnkellbaldurs.github.io\\index2.html","resolved":"c:\\Users\\kotka\\Dev\\hrafnkellbaldurs.github.io\\hrafnkellbaldurs.github.io\\src\\index.js"}],"generated":{"html":"<!DOCTYPE html><!--[if lt IE 8 ]><html class=\"no-js ie ie7\" lang=\"en\"> <![endif]--><!--[if IE 8 ]><html class=\"no-js ie ie8\" lang=\"en\"> <![endif]--><!--[if (gte IE 8)|!(IE)]><!--><html class=\"no-js\" lang=\"en\">  <html> <head>  <meta charset=\"utf-8\"> <title>Hrafnkell Baldursson</title> <meta name=\"description\" content=\"Hrafnkell Baldursson\"> <meta name=\"author\" content=\"Hrafnkell Baldursson\">  <meta name=\"viewport\" content=\"width=device-width, initial-scale=1, maximum-scale=1\">    <link rel=\"shortcut icon\" href=\"d0a2488b114f5445a6823a078fa88a80.png\"> </head> <body> <div class=\"container\"></div> </body> <script type=\"text/javascript\" src=\"cb772d3fb398a5b9679c0094ea1f4363.js\"></script> </html></html>"},"hash":"d5900d1f674bbcb7c05be9923d40c475","cacheData":{}}